{
    "batch_size": 32,
    "best_eval_metric": 19.211429595947266,
    "best_increase_batch_size_eval_metric": Infinity,
    "best_reduce_learning_rate_eval_metric": Infinity,
    "epoch": 2,
    "last_improvement": 0,
    "last_improvement_epoch": 2,
    "last_increase_batch_size": 0,
    "last_increase_batch_size_epoch": 0,
    "last_increase_batch_size_eval_metric_improvement": 0,
    "last_learning_rate_reduction": 0,
    "last_learning_rate_reduction_epoch": 0,
    "last_reduce_learning_rate_eval_metric_improvement": 0,
    "learning_rate": 1e-05,
    "num_increases_batch_size": 0,
    "num_reductions_learning_rate": 0,
    "steps": 4336,
    "test_metrics": {
        "PREDICT_0_C": {
            "accuracy": [],
            "hits_at_k": [],
            "loss": []
        },
        "PREDICT_1_C": {
            "accuracy": [],
            "hits_at_k": [],
            "loss": []
        },
        "PREDICT_2_C": {
            "accuracy": [],
            "hits_at_k": [],
            "loss": []
        },
        "PREDICT_3_C": {
            "accuracy": [],
            "hits_at_k": [],
            "loss": []
        },
        "PREDICT_4_C": {
            "accuracy": [],
            "hits_at_k": [],
            "loss": []
        },
        "PREDICT_5_C": {
            "accuracy": [],
            "hits_at_k": [],
            "loss": []
        },
        "PREDICT_6_C": {
            "accuracy": [],
            "hits_at_k": [],
            "loss": []
        },
        "PREDICT_7_C": {
            "accuracy": [],
            "hits_at_k": [],
            "loss": []
        },
        "PREDICT_8_C": {
            "accuracy": [],
            "hits_at_k": [],
            "loss": []
        },
        "combined": {
            "loss": []
        }
    },
    "train_metrics": {
        "PREDICT_0_C": {
            "accuracy": [
                0.05138960853219032,
                0.08664879202842712
            ],
            "hits_at_k": [
                0.7494089603424072,
                0.8664014339447021
            ],
            "loss": [
                5.861451148986816,
                5.56805419921875
            ]
        },
        "PREDICT_1_C": {
            "accuracy": [
                0.27326586842536926,
                0.3278123736381531
            ],
            "hits_at_k": [
                0.9628812670707703,
                0.9697572588920593
            ],
            "loss": [
                6.110785961151123,
                5.760171890258789
            ]
        },
        "PREDICT_2_C": {
            "accuracy": [
                0.2086000144481659,
                0.2602779269218445
            ],
            "hits_at_k": [
                0.7951767444610596,
                0.8098223805427551
            ],
            "loss": [
                5.311342716217041,
                4.8829240798950195
            ]
        },
        "PREDICT_3_C": {
            "accuracy": [
                0.26804763078689575,
                0.33772993087768555
            ],
            "hits_at_k": [
                0.7366805076599121,
                0.7336100935935974
            ],
            "loss": [
                4.445013046264648,
                4.064437389373779
            ]
        },
        "PREDICT_4_C": {
            "accuracy": [
                0.2744623124599457,
                0.2865709364414215
            ],
            "hits_at_k": [
                0.8375281095504761,
                0.9090266823768616
            ],
            "loss": [
                5.044487476348877,
                4.706491947174072
            ]
        },
        "PREDICT_5_C": {
            "accuracy": [
                0.2940235137939453,
                0.30900076031684875
            ],
            "hits_at_k": [
                0.7128092050552368,
                0.8546820282936096
            ],
            "loss": [
                4.335094451904297,
                4.052716255187988
            ]
        },
        "PREDICT_6_C": {
            "accuracy": [
                0.3149974048137665,
                0.33259817957878113
            ],
            "hits_at_k": [
                0.8805714249610901,
                0.936400830745697
            ],
            "loss": [
                2.9789891242980957,
                2.8797457218170166
            ]
        },
        "PREDICT_7_C": {
            "accuracy": [
                0.3027878701686859,
                0.32553479075431824
            ],
            "hits_at_k": [
                0.7448538541793823,
                0.8252465128898621
            ],
            "loss": [
                2.591107130050659,
                2.4296653270721436
            ]
        },
        "PREDICT_8_C": {
            "accuracy": [
                0.3040708005428314,
                0.3144640624523163
            ],
            "hits_at_k": [
                0.9293807148933411,
                0.9642074704170227
            ],
            "loss": [
                2.0005087852478027,
                1.8921409845352173
            ]
        },
        "combined": {
            "loss": [
                56.12043380737305,
                52.64139938354492
            ]
        }
    },
    "vali_metrics": {
        "PREDICT_0_C": {
            "accuracy": [
                0.032853864133358,
                0.05919097736477852
            ],
            "hits_at_k": [
                0.700465977191925,
                0.8299567699432373
            ],
            "loss": [
                2.4316694736480713,
                2.259721040725708
            ]
        },
        "PREDICT_1_C": {
            "accuracy": [
                0.26586979627609253,
                0.3229673206806183
            ],
            "hits_at_k": [
                0.9857509732246399,
                0.9875405430793762
            ],
            "loss": [
                2.126868963241577,
                2.0180258750915527
            ]
        },
        "PREDICT_2_C": {
            "accuracy": [
                0.20846839249134064,
                0.2831915318965912
            ],
            "hits_at_k": [
                0.8059832453727722,
                0.8188141584396362
            ],
            "loss": [
                2.431394577026367,
                2.2075271606445312
            ]
        },
        "PREDICT_3_C": {
            "accuracy": [
                0.2726566791534424,
                0.32654646039009094
            ],
            "hits_at_k": [
                0.7349743247032166,
                0.7247433662414551
            ],
            "loss": [
                2.616933822631836,
                2.4137942790985107
            ]
        },
        "PREDICT_4_C": {
            "accuracy": [
                0.3003106415271759,
                0.31212857365608215
            ],
            "hits_at_k": [
                0.8673689961433411,
                0.9228457808494568
            ],
            "loss": [
                2.113987922668457,
                1.9893282651901245
            ]
        },
        "PREDICT_5_C": {
            "accuracy": [
                0.31057536602020264,
                0.3087857961654663
            ],
            "hits_at_k": [
                0.7455092072486877,
                0.880368709564209
            ],
            "loss": [
                2.1779727935791016,
                2.051513910293579
            ]
        },
        "PREDICT_6_C": {
            "accuracy": [
                0.3400188982486725,
                0.3626418113708496
            ],
            "hits_at_k": [
                0.8877971172332764,
                0.9380402565002441
            ],
            "loss": [
                1.9985250234603882,
                1.9358456134796143
            ]
        },
        "PREDICT_7_C": {
            "accuracy": [
                0.3384319245815277,
                0.3482239246368408
            ],
            "hits_at_k": [
                0.7589816451072693,
                0.8443409204483032
            ],
            "loss": [
                2.028754711151123,
                1.9333587884902954
            ]
        },
        "PREDICT_8_C": {
            "accuracy": [
                0.30429497361183167,
                0.30949485301971436
            ],
            "hits_at_k": [
                0.9411804676055908,
                0.9611021280288696
            ],
            "loss": [
                1.7472177743911743,
                1.67787504196167
            ]
        },
        "combined": {
            "loss": [
                20.46514320373535,
                19.211429595947266
            ]
        }
    }
}